{
  "openapi": "3.0.0",
  "info": {
    "title": "p7-groupomania",
    "description": "API du projet 7 fait sous NodeJS",
    "contact": {
      "name": "DUMONT Benoit",
      "email": "benoit.dum74@gmail.com"
    },
    "version": "1.0.0"
  },
  "servers": [
    {
      "url": "http://localhost:3000/"
    }
  ],
  "tags": [
    {
      "name": "user",
      "description": "The set of routes for the user"
    },
    {
      "name": "stack",
      "description": "The set of routes for the stack"
    },
    {
      "name": "useragent",
      "description": "The set of routes for the useragent"
    },
    {
      "name": "job",
      "description": "The set of routes for the job"
    },
    {
      "name": "waitlist",
      "description": "The set of routes for the waitlist"
    }
  ],
  "paths": {
    "/api/user/signup": {
      "post": {
        "tags": ["user"],
        "description": "",
        "requestBody": {
          "required": true,
          "content": {
            "application/json": {
              "schema": {
                "$ref": "#/components/schemas/User"
              }
            },
            "multipart/form-data": {
              "schema": {
                "$ref": "#/components/schemas/UserWithAvatar"
              }
            }
          }
        },
        "responses": {
          "201": {
            "description": "Created",
            "content": {
              "application/json": {
                "schema": {
                  "type": "object",
                  "properties": {
                    "message": {
                      "type": "string",
                      "example": "User Created Successfully with an Gravatar image"
                    }
                  }
                }
              },
              "multipart/form-data": {
                "schema": {
                  "type": "object",
                  "properties": {
                    "message": {
                      "type": "string",
                      "example": "User Created Successfully with an Uploaded Image"
                    }
                  }
                }
              }
            }
          },
          "400": {
            "description": "Bad Request",
            "content": {
              "application/json": {
                "schema": {
                  "type": "object",
                  "properties": {
                    "errors": {
                      "type": "object",
                      "properties": {
                        "username": {
                          "type": "string",
                          "example": "Username format is incorrect"
                        },
                        "email": {
                          "type": "string",
                          "example": "Email format is incorrect"
                        },
                        "password": {
                          "type": "string",
                          "example": "Password format is incorrect"
                        },
                        "question": {
                          "type": "string",
                          "example": "Question format is incorrect"
                        },
                        "awswer": {
                          "type": "string",
                          "example": "Awswer format is incorrect"
                        }
                      }
                    }
                  }
                }
              }
            }
          },
          "409": {
            "description": "Conflict",
            "content": {
              "application/json": {
                "schema": {
                  "type": "object",
                  "oneOf": [
                    {
                      "type": "object",
                      "properties": {
                        "error": {
                          "type": "string",
                          "example": "Email already exists"
                        }
                      }
                    },
                    {
                      "type": "object",
                      "properties": {
                        "error": {
                          "type": "string",
                          "example": "Username already exists"
                        }
                      }
                    }
                  ]
                }
              }
            }
          },
          "500": {
            "description": "Internal Server Error",
            "content": {
              "application/json": {
                "schema": {
                  "type": "object",
                  "oneOf": [
                    {
                      "type": "object",
                      "properties": {
                        "error": {
                          "type": "string",
                          "example": "Fetch Gravatar Failed"
                        }
                      }
                    },
                    {
                      "type": "object",
                      "properties": {
                        "error": {
                          "type": "string",
                          "example": "Something happened during the user creation process, please try again"
                        }
                      }
                    }
                  ]
                }
              }
            }
          }
        }
      }
    },
    "/api/user/login": {
      "post": {
        "tags": ["user"],
        "description": "",
        "requestBody": {
          "required": true,
          "content": {
            "application/json": {
              "schema": {
                "oneOf": [
                  {
                    "$ref": "#/components/schemas/LoginWithUsername"
                  },
                  {
                    "$ref": "#/components/schemas/LoginWithEmail"
                  }
                ]
              }
            }
          }
        },
        "responses": {
          "200": {
            "description": "OK",
            "content": {
              "application/json": {
                "schema": {
                  "type": "object",
                  "properties": {
                    "user": {
                      "$ref": "#/components/schemas/UserStructure"
                    },
                    "token": {
                      "type": "string"
                    }
                  }
                }
              }
            }
          },
          "400": {
            "description": "Bad Request",
            "content": {
              "application/json": {
                "schema": {
                  "type": "object",
                  "properties": {
                    "errors": {
                      "type": "object",
                      "properties": {
                        "username": {
                          "type": "string",
                          "example": "Username format is incorrect"
                        },
                        "email": {
                          "type": "string",
                          "example": "Email format is incorrect"
                        },
                        "password": {
                          "type": "string",
                          "example": "Password format is incorrect"
                        }
                      }
                    }
                  }
                }
              }
            }
          },
          "401": {
            "description": "Unauthorized",
            "content": {
              "application/json": {
                "schema": {
                  "type": "object",
                  "properties": {
                    "error": {
                      "type": "string",
                      "example": "Failed to login"
                    }
                  }
                }
              }
            }
          },
          "404": {
            "description": "Not Found",
            "content": {
              "application/json": {
                "schema": {
                  "type": "object",
                  "oneOf": [
                    {
                      "type": "string",
                      "example": "Username not found"
                    },
                    {
                      "type": "string",
                      "example": "Email not found"
                    }
                  ]
                }
              }
            }
          },
          "500": {
            "description": "Internal server Error",
            "content": {
              "application/json": {
                "schema": {
                  "type": "object",
                  "properties": {
                    "error": {
                      "type": "string",
                      "example": "Something happened during the login process, please try again"
                    }
                  }
                }
              }
            }
          }
        }
      }
    },
    "/api/user/forgot": {
      "post": {
        "tags": ["user"],
        "description": "",
        "requestBody": {
          "required": true,
          "content": {
            "application/json": {
              "schema": {
                "$ref": "#/components/schemas/Forgot"
              }
            }
          }
        },
        "responses": {
          "200": {
            "description": "OK",
            "content": {
              "application/json": {
                "schema": {
                  "type": "string",
                  "$ref": "#/components/schemas/ForgotResponse"
                }
              }
            }
          },
          "400": {
            "description": "Bad Request",
            "content": {
              "application/json": {
                "schema": {
                  "type": "object",
                  "properties": {
                    "errors": {
                      "type": "object",
                      "properties": {
                        "email": {
                          "type": "string",
                          "example": "Email format is incorrect"
                        }
                      }
                    }
                  }
                }
              }
            }
          },
          "404": {
            "description": "Not Found",
            "content": {
              "application/json": {
                "schema": {
                  "type": "object",
                  "properties": {
                    "message": {
                      "type": "string",
                      "example": "Email not related to an account"
                    }
                  }
                }
              }
            }
          },
          "500": {
            "description": "Internal Server Error",
            "content": {
              "application/json": {
                "schema": {
                  "type": "object",
                  "properties": {
                    "message": {
                      "type": "string",
                      "example": "Something happened during the forgot process, please try again"
                    }
                  }
                }
              }
            }
          }
        }
      }
    },
    "/api/user/forgot/modify": {
      "post": {
        "tags": ["user"],
        "description": "",
        "requestBody": {
          "required": true,
          "content": {
            "application/json": {
              "schema": {
                "$ref": "#/components/schemas/ForgotModify"
              }
            }
          }
        },
        "responses": {
          "200": {
            "description": "Not Found",
            "content": {
              "application/json": {
                "schema": {
                  "type": "object",
                  "properties": {
                    "message": {
                      "type": "string",
                      "example": "Password updated successfully"
                    }
                  }
                }
              }
            }
          },
          "400": {
            "description": "Bad Request",
            "content": {
              "application/json": {
                "schema": {
                  "type": "object",
                  "properties": {
                    "errors": {
                      "type": "object",
                      "properties": {
                        "email": {
                          "type": "string",
                          "example": "Email format is incorrect"
                        },
                        "awswer": {
                          "type": "string",
                          "example": "Awswer format is incorrect"
                        },
                        "password": {
                          "type": "string",
                          "example": "Password format is incorrect"
                        },
                        "compareResponse": {
                          "type": "string",
                          "example": "This awswer is false"
                        }
                      }
                    }
                  }
                }
              }
            }
          },
          "404": {
            "description": "Not Found",
            "content": {
              "application/json": {
                "schema": {
                  "type": "object",
                  "properties": {
                    "message": {
                      "type": "string",
                      "example": "Email isn't related to an account"
                    }
                  }
                }
              }
            }
          },
          "409": {
            "description": "Conflict",
            "content": {
              "application/json": {
                "schema": {
                  "type": "object",
                  "properties": {
                    "message": {
                      "type": "string",
                      "example": "Your new password cannot be the same than your old password"
                    }
                  }
                }
              }
            }
          },
          "500": {
            "description": "Internal Server Error",
            "content": {
              "application/json": {
                "schema": {
                  "type": "object",
                  "properties": {
                    "errors": {
                      "type": "object",
                      "properties": {
                        "hashPassword": {
                          "type": "string",
                          "example": "Failed to hash your password, please try again"
                        },
                        "message": {
                          "type": "string",
                          "example": "Something happened during the login password reset process, please try again"
                        }
                      }
                    }
                  }
                }
              }
            }
          }
        }
      }
    },
    "/api/user": {
      "get": {
        "tags": ["user"],
        "description": "",
        "security": [
          {
            "bearerAuth": []
          }
        ],
        "responses": {
          "200": {
            "description": "OK",
            "content": {
              "application/json": {
                "schema": {
                  "type": "array",
                  "items": {
                    "$ref": "#/components/schemas/UserStructure"
                  }
                }
              }
            }
          },
          "500": {
            "description": "Internal server Error",
            "content": {
              "application/json": {
                "schema": {
                  "type": "object",
                  "properties": {
                    "error": {
                      "type": "string",
                      "example": "Something happened during getting all users, please try again"
                    }
                  }
                }
              }
            }
          }
        }
      },
      "post": {
        "tags": ["user"],
        "description": "",
        "security": [
          {
            "bearerAuth": []
          }
        ],
        "requestBody": {
          "required": true,
          "content": {
            "application/json": {
              "schema": {
                "$ref": "#/components/schemas/User"
              }
            },
            "multipart/form-data": {
              "schema": {
                "$ref": "#/components/schemas/UserWithAvatar"
              }
            }
          }
        },
        "responses": {
          "201": {
            "description": "Created",
            "content": {
              "application/json": {
                "schema": {
                  "type": "object",
                  "properties": {
                    "message": {
                      "type": "string",
                      "example": "User Created Successfully with an Gravatar image"
                    }
                  }
                }
              },
              "multipart/form-data": {
                "schema": {
                  "type": "object",
                  "properties": {
                    "message": {
                      "type": "string",
                      "example": "User Created Successfully with an Uploaded Image"
                    }
                  }
                }
              }
            }
          },
          "400": {
            "description": "Bad Request",
            "content": {
              "application/json": {
                "schema": {
                  "type": "object",
                  "properties": {
                    "errors": {
                      "type": "object",
                      "properties": {
                        "username": {
                          "type": "string",
                          "example": "Username format is incorrect"
                        },
                        "email": {
                          "type": "string",
                          "example": "Username format is incorrect"
                        },
                        "password": {
                          "type": "string",
                          "example": "Password format is incorrect"
                        },
                        "question": {
                          "type": "string",
                          "example": "Question format is incorrect"
                        },
                        "awswer": {
                          "type": "string",
                          "example": "Reponse format is incorrect"
                        }
                      }
                    }
                  }
                }
              }
            }
          },
          "401": {
            "description": "Unauthorized",
            "content": {
              "application/json": {
                "schema": {
                  "type": "object",
                  "properties": {
                    "message": {
                      "type": "string",
                      "example": "You're not logged in"
                    }
                  }
                }
              }
            }
          },
          "409": {
            "description": "Conflict",
            "content": {
              "application/json": {
                "schema": {
                  "type": "object",
                  "oneOf": [
                    {
                      "type": "object",
                      "properties": {
                        "error": {
                          "type": "string",
                          "example": "Email already exists"
                        }
                      }
                    },
                    {
                      "type": "object",
                      "properties": {
                        "error": {
                          "type": "string",
                          "example": "Username already exists"
                        }
                      }
                    }
                  ]
                }
              }
            }
          },
          "500": {
            "description": "Internal Server Error",
            "content": {
              "application/json": {
                "schema": {
                  "type": "object",
                  "properties": {
                    "message": {
                      "type": "string",
                      "example": "Something happened during the user creation process, please try again"
                    }
                  }
                }
              }
            }
          }
        }
      }
    },
    "/api/user/me": {
      "get": {
        "tags": ["user"],
        "description": "",
        "security": [
          {
            "bearerAuth": []
          }
        ],
        "responses": {
          "200": {
            "description": "OK",
            "content": {
              "application/json": {
                "schema": {
                  "type": "object",
                  "properties": {
                    "user": {
                      "$ref": "#/components/schemas/UserStructure"
                    }
                  }
                }
              }
            }
          },
          "401": {
            "description": "Unauthorized",
            "content": {
              "application/json": {
                "schema": {
                  "type": "object",
                  "properties": {
                    "error": {
                      "type": "string",
                      "example": "You're not logged in"
                    }
                  }
                }
              }
            }
          },
          "403": {
            "description": "Forbidden",
            "content": {
              "application/json": {
                "schema": {
                  "type": "object",
                  "properties": {
                    "error": {
                      "type": "string",
                      "example": "You don't are the person you pretend to be"
                    }
                  }
                }
              }
            }
          },
          "404": {
            "description": "Not Found",
            "content": {
              "application/json": {
                "schema": {
                  "type": "object",
                  "properties": {
                    "error": {
                      "type": "string",
                      "example": "User doesn't exist"
                    }
                  }
                }
              }
            }
          }
        }
      }
    },
    "/api/user/{UserId}": {
      "get": {
        "tags": ["user"],
        "description": "",
        "parameters": [
          {
            "in": "path",
            "name": "UserId",
            "schema": {
              "type": "integer",
              "format": "int32"
            },
            "required": true,
            "description": "ID of user"
          }
        ],
        "security": [
          {
            "bearerAuth": []
          }
        ],
        "responses": {
          "200": {
            "description": "OK",
            "content": {
              "application/json": {
                "schema": {
                  "type": "object",
                  "properties": {
                    "user": {
                      "$ref": "#/components/schemas/UserStructure"
                    }
                  }
                }
              }
            }
          },
          "401": {
            "description": "Unauthorized",
            "content": {
              "application/json": {
                "schema": {
                  "type": "object",
                  "properties": {
                    "error": {
                      "type": "string",
                      "example": "You're not logged in"
                    }
                  }
                }
              }
            }
          },
          "404": {
            "description": "Not Found",
            "content": {
              "application/json": {
                "schema": {
                  "type": "object",
                  "properties": {
                    "error": {
                      "type": "string",
                      "example": "User not found"
                    }
                  }
                }
              }
            }
          }
        }
      },
      "patch": {
        "tags": ["user"],
        "description": "",
        "parameters": [
          {
            "in": "path",
            "name": "UserId",
            "schema": {
              "type": "integer",
              "format": "int32"
            },
            "required": true,
            "description": "ID of user"
          }
        ],
        "security": [
          {
            "bearerAuth": []
          }
        ],
        "requestBody": {
          "required": true,
          "content": {
            "application/json": {
              "schema": {
                "$ref": "#/components/schemas/User"
              }
            },
            "multipart/form-data": {
              "schema": {
                "$ref": "#/components/schemas/UserWithAvatar"
              }
            }
          }
        },
        "responses": {
          "200": {
            "description": "OK",
            "content": {
              "application/json": {
                "schema": {
                  "type": "object",
                  "properties": {
                    "message": {
                      "type": "string",
                      "example": "User has been modified"
                    }
                  }
                }
              }
            }
          },
          "400": {
            "description": "Bad Request",
            "content": {
              "application/json": {
                "schema": {
                  "type": "object",
                  "properties": {
                    "errors": {
                      "type": "object",
                      "properties": {
                        "username": {
                          "type": "string",
                          "example": "Username format is incorrect"
                        },
                        "email": {
                          "type": "string",
                          "example": "Email format is incorrect"
                        },
                        "password": {
                          "type": "string",
                          "example": "Password format is incorrect"
                        },
                        "question": {
                          "type": "string",
                          "example": "Question format is incorrect"
                        },
                        "awswer": {
                          "type": "string",
                          "example": "Awswer format is incorrect"
                        }
                      }
                    }
                  }
                }
              }
            }
          },
          "401": {
            "description": "OK",
            "content": {
              "application/json": {
                "schema": {
                  "type": "object",
                  "properties": {
                    "message": {
                      "type": "string",
                      "example": "You're not logged in"
                    }
                  }
                }
              }
            }
          },
          "404": {
            "description": "Not Found",
            "content": {
              "application/json": {
                "schema": {
                  "type": "object",
                  "properties": {
                    "error": {
                      "type": "string",
                      "example": "User Not found"
                    }
                  }
                }
              }
            }
          },
          "409": {
            "description": "Conflict",
            "content": {
              "application/json": {
                "schema": {
                  "type": "object",
                  "properties": {
                    "error": {
                      "type": "string",
                      "example": "Email already exists"
                    }
                  }
                }
              }
            }
          },
          "500": {
            "description": "Internal Server Error",
            "content": {
              "application/json": {
                "schema": {
                  "type": "object",
                  "properties": {
                    "error": {
                      "type": "string",
                      "example": "Something happened during modifying the user selected, please try again"
                    }
                  }
                }
              }
            }
          }
        }
      },
      "delete": {
        "tags": ["user"],
        "description": "",
        "parameters": [
          {
            "in": "path",
            "name": "UserId",
            "schema": {
              "type": "integer",
              "format": "int32"
            },
            "required": true,
            "description": "ID of user"
          }
        ],
        "security": [
          {
            "bearerAuth": []
          }
        ],
        "responses": {
          "200": {
            "description": "OK",
            "content": {
              "application/json": {
                "schema": {
                  "type": "object",
                  "properties": {
                    "error": {
                      "type": "string",
                      "example": "User has been deleted"
                    }
                  }
                }
              }
            }
          },
          "401": {
            "description": "OK",
            "content": {
              "application/json": {
                "schema": {
                  "type": "object",
                  "properties": {
                    "message": {
                      "type": "string",
                      "example": "You're not logged in"
                    }
                  }
                }
              }
            }
          },
          "404": {
            "description": "Not Found",
            "content": {
              "application/json": {
                "schema": {
                  "type": "object",
                  "properties": {
                    "error": {
                      "type": "string",
                      "example": "User not found"
                    }
                  }
                }
              }
            }
          },
          "500": {
            "description": "Internal Server Error",
            "content": {
              "application/json": {
                "schema": {
                  "type": "object",
                  "properties": {
                    "error": {
                      "type": "string",
                      "example": "Something happened during deleting the user selected, please try again"
                    }
                  }
                }
              }
            }
          }
        }
      }
    },
    "/api/stack": {
      "get": {
        "tags": ["stack"],
        "description": "",
        "security": [
          {
            "bearerAuth": []
          }
        ],
        "responses": {
          "200": {
            "description": "OK",
            "content": {
              "application/json": {
                "schema": {
                  "type": "array",
                  "items": {
                    "$ref": "#/components/schemas/StackStructure"
                  }
                }
              }
            }
          },
          "500": {
            "description": "Internal server Error",
            "content": {
              "application/json": {
                "schema": {
                  "type": "object",
                  "properties": {
                    "error": {
                      "type": "string",
                      "example": "Cannot get Stacks. Please try again."
                    }
                  }
                }
              }
            }
          }
        }
      },
      "post": {
        "tags": ["stack"],
        "description": "",
        "security": [
          {
            "bearerAuth": []
          }
        ],
        "requestBody": {
          "required": true,
          "content": {
            "application/json": {
              "schema": {
                "$ref": "#/components/schemas/Stack"
              }
            }
          }
        },
        "responses": {
          "201": {
            "description": "Created",
            "content": {
              "application/json": {
                "schema": {
                  "type": "object",
                  "properties": {
                    "message": {
                      "type": "string",
                      "example": "Stack Created"
                    }
                  }
                }
              }
            }
          },
          "400": {
            "description": "Bad Request",
            "content": {
              "application/json": {
                "schema": {
                  "type": "object",
                  "properties": {
                    "message": {
                      "type": "string",
                      "example": "Name format is incorrect"
                    }
                  }
                }
              }
            }
          },
          "401": {
            "description": "Unauthorized",
            "content": {
              "application/json": {
                "schema": {
                  "type": "object",
                  "properties": {
                    "message": {
                      "type": "string",
                      "example": "You're not logged in"
                    }
                  }
                }
              }
            }
          },
          "409": {
            "description": "Conflict",
            "content": {
              "application/json": {
                "schema": {
                  "type": "object",
                  "properties": {
                    "message": {
                      "type": "string",
                      "example": "Name has already been used"
                    }
                  }
                }
              }
            }
          },
          "500": {
            "description": "Internal Server Error",
            "content": {
              "application/json": {
                "schema": {
                  "type": "object",
                  "properties": {
                    "message": {
                      "type": "string",
                      "example": "Something happened during the stack creation process, please try again"
                    }
                  }
                }
              }
            }
          }
        }
      }
    },
    "/api/stack/{StackId}": {
      "get": {
        "tags": ["stack"],
        "description": "",
        "parameters": [
          {
            "in": "path",
            "name": "StackId",
            "schema": {
              "type": "integer",
              "format": "int32"
            },
            "required": true,
            "description": "ID of the stack"
          }
        ],
        "security": [
          {
            "bearerAuth": []
          }
        ],
        "responses": {
          "200": {
            "description": "OK",
            "content": {
              "application/json": {
                "schema": {
                  "type": "object",
                  "properties": {
                    "user": {
                      "$ref": "#/components/schemas/StackStructure"
                    }
                  }
                }
              }
            }
          },
          "401": {
            "description": "Unauthorized",
            "content": {
              "application/json": {
                "schema": {
                  "type": "object",
                  "properties": {
                    "message": {
                      "type": "string",
                      "example": "You're not logged in"
                    }
                  }
                }
              }
            }
          },
          "404": {
            "description": "Not Found",
            "content": {
              "application/json": {
                "schema": {
                  "type": "object",
                  "properties": {
                    "message": {
                      "type": "string",
                      "example": "User not found"
                    }
                  }
                }
              }
            }
          },
          "500": {
            "description": "Internal Server Error",
            "content": {
              "application/json": {
                "schema": {
                  "type": "object",
                  "properties": {
                    "message": {
                      "type": "string",
                      "example": "Something happened during the getOneStack process, please try again'"
                    }
                  }
                }
              }
            }
          }
        }
      },
      "patch": {
        "tags": ["stack"],
        "description": "",
        "parameters": [
          {
            "in": "path",
            "name": "StackId",
            "schema": {
              "type": "integer",
              "format": "int32"
            },
            "required": true,
            "description": "ID of the stack"
          }
        ],
        "security": [
          {
            "bearerAuth": []
          }
        ],
        "requestBody": {
          "required": true,
          "content": {
            "application/json": {
              "schema": {
                "$ref": "#/components/schemas/Stack"
              }
            }
          }
        },
        "responses": {
          "200": {
            "description": "OK",
            "content": {
              "application/json": {
                "schema": {
                  "type": "object",
                  "properties": {
                    "message": {
                      "type": "string",
                      "example": "Stack has been modified"
                    }
                  }
                }
              }
            }
          },
          "400": {
            "description": "Bad Request",
            "content": {
              "application/json": {
                "schema": {
                  "type": "object",
                  "properties": {
                    "errors": {
                      "type": "object",
                      "properties": {
                        "name": {
                          "type": "string",
                          "example": "Name format is incorrect"
                        }
                      }
                    }
                  }
                }
              }
            }
          },
          "401": {
            "description": "OK",
            "content": {
              "application/json": {
                "schema": {
                  "type": "object",
                  "properties": {
                    "message": {
                      "type": "string",
                      "example": "You're not logged in"
                    }
                  }
                }
              }
            }
          },
          "404": {
            "description": "Not Found",
            "content": {
              "application/json": {
                "schema": {
                  "type": "object",
                  "properties": {
                    "error": {
                      "type": "string",
                      "example": "Stack Not found"
                    }
                  }
                }
              }
            }
          },
          "409": {
            "description": "Conflict",
            "content": {
              "application/json": {
                "schema": {
                  "type": "object",
                  "properties": {
                    "error": {
                      "type": "string",
                      "example": "Name already exists"
                    }
                  }
                }
              }
            }
          },
          "500": {
            "description": "Internal Server Error",
            "content": {
              "application/json": {
                "schema": {
                  "type": "object",
                  "properties": {
                    "error": {
                      "type": "string",
                      "example": "Something happened during modifying the stack selected, please try again"
                    }
                  }
                }
              }
            }
          }
        }
      },
      "delete": {
        "tags": ["stack"],
        "description": "",
        "parameters": [
          {
            "in": "path",
            "name": "StackId",
            "schema": {
              "type": "integer",
              "format": "int32"
            },
            "required": true,
            "description": "ID of the stack"
          }
        ],
        "security": [
          {
            "bearerAuth": []
          }
        ],
        "responses": {
          "200": {
            "description": "OK",
            "content": {
              "application/json": {
                "schema": {
                  "type": "object",
                  "properties": {
                    "message": {
                      "type": "string",
                      "example": "Stack has been deleted"
                    }
                  }
                }
              }
            }
          },
          "401": {
            "description": "OK",
            "content": {
              "application/json": {
                "schema": {
                  "type": "object",
                  "properties": {
                    "message": {
                      "type": "string",
                      "example": "You're not logged in"
                    }
                  }
                }
              }
            }
          },
          "404": {
            "description": "Not Found",
            "content": {
              "application/json": {
                "schema": {
                  "type": "object",
                  "properties": {
                    "error": {
                      "type": "string",
                      "example": "Stack not found"
                    }
                  }
                }
              }
            }
          },
          "500": {
            "description": "Internal Server Error",
            "content": {
              "application/json": {
                "schema": {
                  "type": "object",
                  "properties": {
                    "error": {
                      "type": "string",
                      "example": "Something happened during deleting the stack selected, please try again"
                    }
                  }
                }
              }
            }
          }
        }
      }
    },
    "/api/useragent": {
      "get": {
        "tags": ["useragent"],
        "description": "",
        "security": [
          {
            "bearerAuth": []
          }
        ],
        "responses": {
          "200": {
            "description": "OK",
            "content": {
              "application/json": {
                "schema": {
                  "type": "array",
                  "items": {
                    "$ref": "#/components/schemas/UserAgentStructure"
                  }
                }
              }
            }
          },
          "404": {
            "description": "Not Found",
            "content": {
              "application/json": {
                "schema": {
                  "type": "object",
                  "properties": {
                    "message": {
                      "type": "string",
                      "example": "UserAgent not found"
                    }
                  }
                }
              }
            }
          },
          "500": {
            "description": "Internal server Error",
            "content": {
              "application/json": {
                "schema": {
                  "type": "object",
                  "properties": {
                    "error": {
                      "type": "string",
                      "example": "Cannot get the UserAgent. Please try again."
                    }
                  }
                }
              }
            }
          }
        }
      },
      "post": {
        "tags": ["useragent"],
        "description": "",
        "security": [
          {
            "bearerAuth": []
          }
        ],
        "requestBody": {
          "required": true,
          "content": {
            "application/json": {
              "schema": {
                "$ref": "#/components/schemas/UserAgent"
              }
            }
          }
        },
        "responses": {
          "201": {
            "description": "Created",
            "content": {
              "application/json": {
                "schema": {
                  "type": "object",
                  "properties": {
                    "message": {
                      "type": "string",
                      "example": "userAgent Created"
                    }
                  }
                }
              }
            }
          },
          "401": {
            "description": "Unauthorized",
            "content": {
              "application/json": {
                "schema": {
                  "type": "object",
                  "properties": {
                    "message": {
                      "type": "string",
                      "example": "You're not logged in"
                    }
                  }
                }
              }
            }
          },
          "500": {
            "description": "Internal Server Error",
            "content": {
              "application/json": {
                "schema": {
                  "type": "object",
                  "properties": {
                    "message": {
                      "type": "string",
                      "example": "Something happened during the userAgent creation process, please try again"
                    }
                  }
                }
              }
            }
          }
        }
      },
      "patch": {
        "tags": ["useragent"],
        "description": "",
        "security": [
          {
            "bearerAuth": []
          }
        ],
        "requestBody": {
          "required": true,
          "content": {
            "application/json": {
              "schema": {
                "$ref": "#/components/schemas/UserAgent"
              }
            }
          }
        },
        "responses": {
          "201": {
            "description": "Created",
            "content": {
              "application/json": {
                "schema": {
                  "type": "object",
                  "properties": {
                    "message": {
                      "type": "string",
                      "example": "userAgent has been modified"
                    }
                  }
                }
              }
            }
          },
          "401": {
            "description": "Unauthorized",
            "content": {
              "application/json": {
                "schema": {
                  "type": "object",
                  "properties": {
                    "message": {
                      "type": "string",
                      "example": "You're not logged in"
                    }
                  }
                }
              }
            }
          },
          "404": {
            "description": "Not Found",
            "content": {
              "application/json": {
                "schema": {
                  "type": "object",
                  "properties": {
                    "message": {
                      "type": "string",
                      "example": "userAgent not found"
                    }
                  }
                }
              }
            }
          },
          "500": {
            "description": "Internal Server Error",
            "content": {
              "application/json": {
                "schema": {
                  "type": "object",
                  "properties": {
                    "message": {
                      "type": "string",
                      "example": "Something happened during the userAgent modification process, please try again"
                    }
                  }
                }
              }
            }
          }
        }
      }
    },
    "/api/job": {
      "get": {
        "tags": ["job"],
        "description": "",
        "security": [
          {
            "bearerAuth": []
          }
        ],
        "responses": {
          "200": {
            "description": "OK",
            "content": {
              "application/json": {
                "schema": {
                  "type": "array",
                  "items": {
                    "$ref": "#/components/schemas/JobStructure"
                  }
                }
              }
            }
          },
          "500": {
            "description": "Internal server Error",
            "content": {
              "application/json": {
                "schema": {
                  "type": "object",
                  "properties": {
                    "message": {
                      "type": "string",
                      "example": "Something happened during the getAllJobs process, please try again"
                    }
                  }
                }
              }
            }
          }
        }
      }
    },
    "/api/job/last7days": {
      "get": {
        "tags": ["job"],
        "description": "",
        "security": [
          {
            "bearerAuth": []
          }
        ],
        "responses": {
          "200": {
            "description": "OK",
            "content": {
              "application/json": {
                "schema": {
                  "type": "array",
                  "items": {
                    "$ref": "#/components/schemas/JobStructure"
                  }
                }
              }
            }
          },
          "500": {
            "description": "Internal server Error",
            "content": {
              "application/json": {
                "schema": {
                  "type": "object",
                  "properties": {
                    "message": {
                      "type": "string",
                      "example": "Something happened during the getAllJobsLast7Days process, please try again"
                    }
                  }
                }
              }
            }
          }
        }
      }
    },
    "/api/job/:JobId": {
      "get": {
        "tags": ["job"],
        "description": "",
        "parameters": [
          {
            "in": "path",
            "name": "JobId",
            "schema": {
              "type": "integer",
              "format": "int32"
            },
            "required": true,
            "description": "ID of the job"
          }
        ],
        "security": [
          {
            "bearerAuth": []
          }
        ],
        "responses": {
          "200": {
            "description": "OK",
            "content": {
              "application/json": {
                "schema": {
                  "type": "array",
                  "items": {
                    "$ref": "#/components/schemas/JobStructure"
                  }
                }
              }
            }
          },
          "500": {
            "description": "Internal server Error",
            "content": {
              "application/json": {
                "schema": {
                  "type": "object",
                  "properties": {
                    "message": {
                      "type": "string",
                      "example": "Something happened during the getAllJobs process, please try again"
                    }
                  }
                }
              }
            }
          }
        }
      }
    },
    "/api/waitlist": {
      "get": {
        "tags": ["waitlist"],
        "description": "",
        "security": [
          {
            "bearerAuth": []
          }
        ],
        "responses": {
          "200": {
            "description": "OK",
            "content": {
              "application/json": {
                "schema": {
                  "type": "object",
                  "properties": {
                    "message": {
                      "type": "string",
                      "example": " - WaitList successfully proceded in XXmXX"
                    }
                  }
                }
              }
            }
          }
        }
      }
    },
    "/api/waitlist/crawl": {
      "get": {
        "tags": ["waitlist"],
        "description": "",
        "security": [
          {
            "bearerAuth": []
          }
        ],
        "responses": {
          "200": {
            "description": "OK",
            "content": {
              "application/json": {
                "schema": {
                  "type": "object",
                  "properties": {
                    "message": {
                      "type": "string",
                      "example": " - Crawl successfully completed in XXmXX"
                    }
                  }
                }
              }
            }
          }
        }
      }
    }
  },
  "components": {
    "schemas": {
      "User": {
        "type": "object",
        "properties": {
          "username": {
            "type": "string"
          },
          "email": {
            "type": "string",
            "format": "email"
          },
          "password": {
            "type": "string",
            "format": "password"
          },
          "avatar": {
            "type": "string",
            "format": "url"
          },
          "question": {
            "type": "string"
          },
          "awswer": {
            "type": "string"
          }
        },
        "required": ["username", "email", "password", "question", "awswer"]
      },
      "UserWithAvatar": {
        "type": "object",
        "properties": {
          "username": {
            "type": "string"
          },
          "email": {
            "type": "string",
            "format": "email"
          },
          "password": {
            "type": "string",
            "format": "password"
          },
          "avatar": {
            "type": "string",
            "format": "binary"
          },
          "question": {
            "type": "string"
          },
          "awswer": {
            "type": "string"
          }
        },
        "required": ["username", "email", "password", "question", "awswer"]
      },
      "LoginWithEmail": {
        "type": "object",
        "properties": {
          "email": {
            "type": "string",
            "format": "email"
          },
          "password": {
            "type": "string",
            "format": "password"
          }
        }
      },
      "LoginWithUsername": {
        "type": "object",
        "properties": {
          "username": {
            "type": "string"
          },
          "password": {
            "type": "string",
            "format": "password"
          }
        }
      },
      "UserStructure": {
        "type": "object",
        "properties": {
          "id": {
            "type": "integer"
          },
          "username": {
            "type": "string"
          },
          "email": {
            "type": "string",
            "format": "email"
          },
          "password": {
            "type": "string",
            "format": "password"
          },
          "question": {
            "type": "string"
          },
          "awswer": {
            "type": "string"
          },
          "rank": {
            "type": "integer"
          },
          "createdAt": {
            "type": "string",
            "format": "date-time"
          },
          "updatedAt": {
            "type": "string",
            "format": "date-time"
          }
        }
      },
      "Forgot": {
        "type": "object",
        "properties": {
          "email": {
            "type": "string",
            "format": "email"
          }
        }
      },
      "ForgotResponse": {
        "type": "object",
        "properties": {
          "response": {
            "type": "string"
          }
        }
      },
      "ForgotModify": {
        "type": "object",
        "properties": {
          "email": {
            "type": "string",
            "format": "email"
          },
          "awswer": {
            "type": "string"
          },
          "password": {
            "type": "string",
            "format": "password"
          }
        }
      },
      "Stack": {
        "type": "object",
        "properties": {
          "name": {
            "type": "string"
          },
          "type": {
            "type": "string"
          },
          "regex": {
            "type": "string"
          }
        }
      },
      "StackStructure": {
        "type": "object",
        "properties": {
          "id": {
            "type": "integer"
          },
          "name": {
            "type": "string"
          },
          "type": {
            "type": "string"
          },
          "regex": {
            "type": "string"
          },
          "createdAt": {
            "type": "string",
            "format": "date-time"
          },
          "updatedAt": {
            "type": "string",
            "format": "date-time"
          }
        }
      },
      "UserAgent": {
        "type": "object",
        "properties": {
          "browser": {
            "type": "string"
          },
          "useragent": {
            "type": "string"
          }
        }
      },
      "UserAgentStructure": {
        "type": "object",
        "properties": {
          "id": {
            "type": "integer"
          },
          "browser": {
            "type": "string"
          },
          "useragent": {
            "type": "string"
          },
          "createdAt": {
            "type": "string",
            "format": "date-time"
          },
          "updatedAt": {
            "type": "string",
            "format": "date-time"
          }
        }
      },
      "JobStructure": {
        "type": "object",
        "properties": {
          "id": {
            "type": "integer"
          },
          "name": {
            "type": "string"
          },
          "location": {
            "type": "string"
          },
          "link": {
            "type": "string"
          },
          "contract": {
            "type": "string"
          },
          "salary": {
            "type": "string"
          },
          "remote": {
            "type": "string"
          },
          "exp": {
            "type": "string"
          },
          "study": {
            "type": "string"
          },
          "start": {
            "type": "string"
          },
          "type": {
            "type": "string"
          },
          "origin": {
            "type": "string"
          },
          "createdAt": {
            "type": "string",
            "format": "date-time"
          },
          "updatedAt": {
            "type": "string",
            "format": "date-time"
          }
        }
      }
    },
    "securitySchemes": {
      "bearerAuth": {
        "type": "http",
        "scheme": "bearer",
        "bearerFormat": "JWT"
      }
    }
  }
}
